sunstreaker/__init__.py
sunstreaker/activations.py
sunstreaker/data.py
sunstreaker/layers.py
sunstreaker/losses.py
sunstreaker/metrics.py
sunstreaker/models.py
sunstreaker/optimizers.py
sunstreaker/applications/__init__.py
sunstreaker/engine/__init__.py
sunstreaker/engine/base_layer.py
sunstreaker/engine/functional.py
sunstreaker/engine/input_layer.py
sunstreaker/engine/sequential.py
sunstreaker/engine/training.py
sunstreaker-0.0.1.dev5.dist-info/LICENSE
sunstreaker-0.0.1.dev5.dist-info/METADATA
sunstreaker-0.0.1.dev5.dist-info/WHEEL
sunstreaker-0.0.1.dev5.dist-info/top_level.txt
sunstreaker-0.0.1.dev5.dist-info/RECORD
