Metadata-Version: 2.1
Name: sunstreaker
Version: 0.0.1.dev5
Summary: 源码清晰明了，使用简单好搞
Home-page: https://github.com/duyongan/sunstreaker
Author: duyongan (杜永安)【公众号：无数据不智能】
Author-email: 13261051171@163.com
Classifier: Programming Language :: Python :: 3.10
Requires-Python: >=3.10
License-File: LICENSE
Requires-Dist: matplotlib (==3.6.2)
Requires-Dist: msgpack (==1.0.4)
Requires-Dist: networkx (==2.8.8)
Requires-Dist: pandas (==1.5.1)
Requires-Dist: dill (==0.3.6)
Requires-Dist: tqdm (==4.64.1)
Requires-Dist: numpy (==1.23.4)
